kubeflow/__init__.py
kubeflow/metadata/__init__.py
kubeflow/metadata/metadata.py
tests/__init__.py
tests/test_metadata.py
tests/test_notebook.py
kf_metadata-0.3.1.dist-info/METADATA
kf_metadata-0.3.1.dist-info/WHEEL
kf_metadata-0.3.1.dist-info/top_level.txt
kf_metadata-0.3.1.dist-info/RECORD
